Tool.py
ddtestlib/__init__.py
ddtestlib/ddlibone.py
ddtestlib-1.0.0.dist-info/LICENSE.txt
ddtestlib-1.0.0.dist-info/METADATA
ddtestlib-1.0.0.dist-info/WHEEL
ddtestlib-1.0.0.dist-info/top_level.txt
ddtestlib-1.0.0.dist-info/RECORD
