Metadata-Version: 2.1
Name: ddtestlib
Version: 1.0.0
Summary: this is a niubi lib
Home-page: https://github.com/dongdong2019/Python_code
Author: dd
Author-email: 3425296552@qq.com
License: MIT
Platform: UNKNOWN
